google_images_downloader/__dist_version__.py
google_images_downloader/__init__.py
google_images_downloader/__main__.py
google_images_downloader/__version__.py
google_images_downloader/arguments_helper.py
google_images_downloader/gid.py
google_images_downloader/tests/__init__.py
google_images_downloader/tests/test_arguments_helper.py
google_images_downloader/tests/test_browser.py
google_images_downloader/tests/test_download.py
google_images_downloader/tests/test_main.py
google_images_downloader-1.0.16.dist-info/LICENSE
google_images_downloader-1.0.16.dist-info/METADATA
google_images_downloader-1.0.16.dist-info/WHEEL
google_images_downloader-1.0.16.dist-info/entry_points.txt
google_images_downloader-1.0.16.dist-info/top_level.txt
google_images_downloader-1.0.16.dist-info/RECORD
