Metadata-Version: 2.1
Name: google-images-downloader
Version: 1.0.16
Summary: Script to download images from Google Images queries
Author: Harkame
Project-URL: repository, https://github.com/Harkame/google-images-downloader
Classifier: Programming Language :: Python
Requires-Python: >=3.8
License-File: LICENSE
Requires-Dist: selenium >=4.11.2
Requires-Dist: requests >=2.31.0
Requires-Dist: Pillow >=10.0.0
Requires-Dist: tqdm >=4.66.1
Requires-Dist: psutil >=5.9.5
Provides-Extra: dev
Requires-Dist: pytest >=7 ; extra == 'dev'
Requires-Dist: pytest-cov >=4.1.0 ; extra == 'dev'
